geoprocessing/__init__.py
geoprocessing/coords_utils.py
geoprocessing/file_utils.py
geoprocessing/geom_utils.py
geoprocessing/order_directions.py
geoprocessing/process_directions.py
geoprocessing/process_distance.py
geoprocessing/process_intersections.py
geoprocessing-3.1.6.dist-info/METADATA
geoprocessing-3.1.6.dist-info/WHEEL
geoprocessing-3.1.6.dist-info/top_level.txt
geoprocessing-3.1.6.dist-info/RECORD
