Metadata-Version: 2.1
Name: geoprocessing
Version: 3.1.6
Summary: Geoprocessing Library
Home-page: https://ci.clearroadlab.io/clearroad/pygeoprocessing.git
Author: Arman Davidyan
Author-email: arman.davidyan@clearroad.io
License: unlicense
Requires-Dist: requests ==2.32.3
Requires-Dist: python-dateutil ==2.9.0
Requires-Dist: numpy ==2.1.1
Requires-Dist: shapely ==2.0.6
Requires-Dist: fiona ==1.10.1
